[
{"question":"x + 15 = 40, x nec?dir?","options":["24","25","26","27"],"answer":"25"},
{"question":"3 ? 7 + 5 nec?dir?","options":["25","26","27","28"],"answer":"26"},
{"question":"48 ? x = 8, x nec?dir?","options":["5","6","7","8"],"answer":"6"},
{"question":"f(x) = 2x + 3, f(4) nec?dir?","options":["10","11","12","13"],"answer":"11"},
{"question":"Bir ?d?din 20%-i 8-dir. ?d?d nec?dir?","options":["36","38","40","42"],"answer":"40"},
{"question":"2x + 7 = 21, x nec?dir?","options":["6","7","8","9"],"answer":"7"},
{"question":"15 ? 3 - 12 nec?dir?","options":["33","34","35","36"],"answer":"33"},
{"question":"56 ? 7 + 5 nec?dir?","options":["12","13","14","15"],"answer":"13"},
{"question":"f(x) = x? - 2, f(5) nec?dir?","options":["23","24","25","26"],"answer":"23"},
{"question":"Bir ?d?din 15%-i 12-dir. ?d?d nec?dir?","options":["75","78","80","82"],"answer":"80"},
{"question":"x/4 = 6, x nec?dir?","options":["22","23","24","25"],"answer":"24"},
{"question":"7 ? 8 - 10 nec?dir?","options":["45","46","47","46"],"answer":"46"},
{"question":"81 ? 9 + 5 nec?dir?","options":["13","14","15","16"],"answer":"14"},
{"question":"f(x) = 3x - 4, f(6) nec?dir?","options":["13","14","15","16"],"answer":"14"},
{"question":"Bir ?d?din 10%-i 7-dir. ?d?d nec?dir?","options":["60","65","70","75"],"answer":"70"},
{"question":"x - 9 = 27, x nec?dir?","options":["35","36","37","38"],"answer":"36"},
{"question":"12 ? 5 + 18 nec?dir?","options":["77","78","79","80"],"answer":"78"},
{"question":"72 ? 8 - 3 nec?dir?","options":["5","6","7","8"],"answer":"6"},
{"question":"f(x) = x + 10, f(15) nec?dir?","options":["24","25","26","27"],"answer":"25"},
{"question":"Bir ?d?din 25%-i 15-dir. ?d?d nec?dir?","options":["55","58","60","62"],"answer":"60"},
{"question":"3x + 9 = 24, x nec?dir?","options":["4","5","6","7"],"answer":"5"},
{"question":"14 ? 6 - 20 nec?dir?","options":["63","64","65","66"],"answer":"64"},
{"question":"90 ? 9 + 7 nec?dir?","options":["16","17","18","19"],"answer":"17"},
{"question":"f(x) = 2x?, f(3) nec?dir?","options":["17","18","19","20"],"answer":"18"},
{"question":"Bir ?d?din 30%-i 18-dir. ?d?d nec?dir?","options":["55","56","57","60"],"answer":"60"},
{"question":"x/5 + 7 = 15, x nec?dir?","options":["30","32","35","37"],"answer":"40"},
{"question":"8 ? 7 - 14 nec?dir?","options":["41","42","43","44"],"answer":"42"},
{"question":"63 ? 7 + 8 nec?dir?","options":["16","17","18","19"],"answer":"17"},
{"question":"f(x) = x - 4, f(12) nec?dir?","options":["7","8","9","10"],"answer":"8"},
{"question":"Bir ?d?din 12%-i 9-dir. ?d?d nec?dir?","options":["70","72","74","75"],"answer":"75"},
{"question":"2x - 5 = 19, x nec?dir?","options":["10","11","12","13"],"answer":"12"},
{"question":"9 ? 6 + 14 nec?dir?","options":["67","68","69","70"],"answer":"68"},
{"question":"56 ? 8 - 3 nec?dir?","options":["4","5","6","7"],"answer":"4"},
{"question":"f(x) = 3x + 2, f(5) nec?dir?","options":["16","17","18","19"],"answer":"17"},
{"question":"Bir ?d?din 40%-i 32-dir. ?d?d nec?dir?","options":["78","80","82","84"],"answer":"80"},
{"question":"x + 23 = 58, x nec?dir?","options":["34","35","36","37"],"answer":"35"},
{"question":"11 ? 7 - 15 nec?dir?","options":["61","62","63","64"],"answer":"62"},
{"question":"72 ? 6 + 9 nec?dir?","options":["20","21","22","23"],"answer":"21"},
{"question":"f(x) = x? - 5, f(6) nec?dir?","options":["30","31","32","33"],"answer":"31"},
{"question":"Bir ?d?din 18%-i 9-dir. ?d?d nec?dir?","options":["48","50","52","54"],"answer":"50"},
{"question":"3x + 12 = 33, x nec?dir?","options":["6","7","8","9"],"answer":"7"},
{"question":"15 ? 4 + 18 nec?dir?","options":["76","77","78","79"],"answer":"78"},
{"question":"81 ? 9 - 5 nec?dir?","options":["3","4","5","6"],"answer":"4"},
{"question":"f(x) = 2x + 5, f(7) nec?dir?","options":["18","19","20","21"],"answer":"19"},
{"question":"Bir ?d?din 50%-i 40-dir. ?d?d nec?dir?","options":["70","75","80","85"],"answer":"80"},
{"question":"x/6 + 8 = 15, x nec?dir?","options":["40","42","44","46"],"answer":"42"},
{"question":"7 ? 9 - 20 nec?dir?","options":["43","44","45","46"],"answer":"43"},
{"question":"64 ? 8 + 6 nec?dir?","options":["13","14","15","16"],"answer":"14"},
{"question":"f(x) = x - 3, f(10) nec?dir?","options":["6","7","8","9"],"answer":"7"},
{"question":"Bir ?d?din 22%-i 11-dir. ?d?d nec?dir?","options":["48","50","52","54"],"answer":"50"},
{"question":"5x + 10 = 35, x nec?dir?","options":["4","5","6","7"],"answer":"5"},
{"question":"12 ? 5 - 8 nec?dir?","options":["50","51","52","53"],"answer":"52"},
{"question":"90 ? 5 + 7 nec?dir?","options":["24","25","26","27"],"answer":"25"},
{"question":"f(x) = 3x - 7, f(6) nec?dir?","options":["10","11","12","13"],"answer":"11"},
{"question":"Bir ?d?din 35%-i 21-dir. ?d?d nec?dir?","options":["58","59","60","61"],"answer":"60"},
{"question":"x - 14 = 29, x nec?dir?","options":["43","44","45","46"],"answer":"43"},
{"question":"13 ? 6 + 9 nec?dir?","options":["86","87","88","89"],"answer":"87"},
{"question":"72 ? 9 + 8 nec?dir?","options":["15","16","17","18"],"answer":"16"},
{"question":"f(x) = 2x? + 1, f(4) nec?dir?","options":["31","32","33","34"],"answer":"33"},
{"question":"Bir ?d?din 28%-i 14-dir. ?d?d nec?dir?","options":["48","49","50","51"],"answer":"50"}
]
